LICENSE
MANIFEST.in
README.md
requirements.txt
setup.cfg
setup.py
pytrees/AVLTree.py
pytrees/BinaryIndexTree.py
pytrees/BinarySearchTree.py
pytrees/IntervalTree.py
pytrees/Trie.py
pytrees/__init__.py
pytrees.egg-info/PKG-INFO
pytrees.egg-info/SOURCES.txt
pytrees.egg-info/dependency_links.txt
pytrees.egg-info/top_level.txt
pytrees/__pycache__/AVLTree.cpython-36.pyc
pytrees/__pycache__/BinaryIndexTree.cpython-36.pyc
pytrees/__pycache__/BinarySearchTree.cpython-36.pyc
pytrees/__pycache__/IntervalTree.cpython-36.pyc
pytrees/__pycache__/Trie.cpython-36.pyc
pytrees/__pycache__/__init__.cpython-36.pyc