Metadata-Version: 1.2
Name: pytrees
Version: 0.0.1
Summary: AVL Tree, Interval Tree, Trie and More. All kinds of Trees implemented in python3. 
Home-page: https://github.com/cool-pot/pytrees
Author: Yi Zhou
Author-email: 601746479@qq.com
Maintainer: Yi Zhou
Maintainer-email: 601746479@qq.com
License: MIT
Download-URL: https://github.com/cool-pot/pytrees/archive/v0.0.1.tar.gz
Platform: Windows
Platform: MacOS
Platform: Unix
Classifier: Development Status :: 4 - Beta
Classifier: Intended Audience :: Developers
Classifier: License :: OSI Approved :: MIT License
Classifier: Natural Language :: English
Classifier: Operating System :: Microsoft :: Windows
Classifier: Operating System :: MacOS
Classifier: Operating System :: Unix
Classifier: Programming Language :: Python :: 3 :: Only
